featuretools4spark/__init__.py
featuretools4spark/featuretools4spark.py
featuretools4spark-0.1.4.dist-info/WHEEL
featuretools4spark-0.1.4.dist-info/METADATA
featuretools4spark-0.1.4.dist-info/RECORD
