Metadata-Version: 2.1
Name: featuretools4spark
Version: 0.1.4
Summary: mimic the interesting value usage
Author: Weixing Li
Author-email: weixing.li@verisk.com
Requires-Python: >=3.6,<4.0
Classifier: Programming Language :: Python :: 3
Classifier: Programming Language :: Python :: 3.6
Classifier: Programming Language :: Python :: 3.7
Classifier: Programming Language :: Python :: 3.8
Classifier: Programming Language :: Python :: 3.9
Requires-Dist: featuretools (>=0.20.0,<0.21.0)
Requires-Dist: pandas (>=1.1.3,<2.0.0)
